shellfs/__init__.py
shellfs/_version.py
shellfs/file.py
shellfs/spec.py
shellfs/shell/__init__.py
shellfs/shell/core.py
shellfs/shell/local.py
shellfs/shell/ssh.py
shellfs/shell/unix.py
shellfs/shell/windows.py
shellfs-0.2.0.dist-info/LICENSE
shellfs-0.2.0.dist-info/METADATA
shellfs-0.2.0.dist-info/WHEEL
shellfs-0.2.0.dist-info/top_level.txt
shellfs-0.2.0.dist-info/zip-safe
shellfs-0.2.0.dist-info/RECORD
