Metadata-Version: 2.1
Name: shellfs
Version: 0.2.0
Summary: Provides a filesystem abstraction based on shell commands
Author-email: Jens Engel <jenisys@noreply.github.com>
License: MIT
Project-URL: Homepage, https://github.com/jenisys/shellfs
Project-URL: Download, https://pypi.org/project/shellfs/
Project-URL: Repository, https://github.com/jenisys/shellfs
Project-URL: Issues, https://github.com/jenisys/shellfs/issues/
Keywords: shellfs,fsspec,filesystem,filesystem-adapter,filesystem-spec
Platform: any
Classifier: Development Status :: 3 - Alpha
Classifier: Intended Audience :: Developers
Classifier: License :: OSI Approved :: MIT License
Classifier: Operating System :: OS Independent
Classifier: Programming Language :: Python :: 3
Classifier: Programming Language :: Python :: 3.8
Classifier: Programming Language :: Python :: 3.9
Classifier: Programming Language :: Python :: 3.10
Classifier: Programming Language :: Python :: 3.11
Classifier: Programming Language :: Python :: 3.12
Classifier: Programming Language :: Python :: 3.13
Classifier: Topic :: System :: Filesystems
Requires-Python: >=3.8
License-File: LICENSE
Requires-Dist: fsspec>=2024.10.0
Requires-Dist: parse>=1.20.2
Requires-Dist: parse-type>=0.6.4
Requires-Dist: typing-extensions>=4.12.2
Provides-Extra: develop
Requires-Dist: setuptools; extra == "develop"
Requires-Dist: setuptools-scm; extra == "develop"
Requires-Dist: wheel; extra == "develop"
Requires-Dist: build>=0.5.1; extra == "develop"
Requires-Dist: twine>=1.13.0; extra == "develop"
Requires-Dist: coverage>=4.4; extra == "develop"
Requires-Dist: pytest>=5.0; extra == "develop"
Requires-Dist: pytest-html>=1.19.0; extra == "develop"
Requires-Dist: pytest-cov; extra == "develop"
Requires-Dist: tox>=4.0; extra == "develop"
Requires-Dist: virtualenv>=20.0.0; extra == "develop"
Requires-Dist: pylint; extra == "develop"
Requires-Dist: ruff; python_version >= "3.7" and extra == "develop"
Provides-Extra: testing
Requires-Dist: pytest>=5.0; extra == "testing"
Requires-Dist: pytest-html>=1.19.0; extra == "testing"
